MinecraftDataHelper/Items.py
MinecraftDataHelper/Recipes.py
MinecraftDataHelper/__init__.py
MinecraftDataHelper/tags.py
mcdatahelper-1.0.0.dist-info/LICENSE
mcdatahelper-1.0.0.dist-info/METADATA
mcdatahelper-1.0.0.dist-info/WHEEL
mcdatahelper-1.0.0.dist-info/top_level.txt
mcdatahelper-1.0.0.dist-info/RECORD
