Metadata-Version: 2.1
Name: mcdatahelper
Version: 1.0.0
Summary: A small minecraft tool
Home-page: https://github.com/DancingSnow0517/MinecraftDataHelper
Author: DancingSnow
Author-email: 1121149616@qq.com
License: UNKNOWN
Project-URL: Bug Tracker, https://github.com/DancingSnow0517/MinecraftDataHelper/issues
Platform: UNKNOWN
Classifier: Programming Language :: Python :: 3
Classifier: License :: OSI Approved :: MIT License
Classifier: Operating System :: OS Independent
Requires-Python: >=3.6
License-File: LICENSE
